toPYD/__init__.py
toPYD/cli.py
toPYD/installer.py
toPYD/toPYD.py
topyd-0.3.dist-info/METADATA
topyd-0.3.dist-info/WHEEL
topyd-0.3.dist-info/entry_points.txt
topyd-0.3.dist-info/RECORD
