Metadata-Version: 2.4
Name: toPYD
Version: 0.3
Summary: 将Python源文件编译为 pyd/so 二进制扩展模块
Project-URL: Homepage, https://github.com/yourusername/your-package-name
Project-URL: Repository, https://github.com/yourusername/your-package-name
Author: GoodIdear
Classifier: License :: OSI Approved :: MIT License
Classifier: Operating System :: OS Independent
Classifier: Programming Language :: Python :: 3
Requires-Python: >=3.8
Requires-Dist: click>=8.0.0
Requires-Dist: cython>=3.0.0
Requires-Dist: pathspec>=0.12.1
Requires-Dist: setuptools>=70.0.0
